odoo8_addon_l10n_ch_qr_bill-8.0.1.0.0.99.dev6-py3.6-nspkg.pth
odoo_addons/l10n_ch_qr_bill/README.rst
odoo_addons/l10n_ch_qr_bill/__init__.py
odoo_addons/l10n_ch_qr_bill/__openerp__.py
odoo_addons/l10n_ch_qr_bill/controllers/__init__.py
odoo_addons/l10n_ch_qr_bill/controllers/main.py
odoo_addons/l10n_ch_qr_bill/data/paperformat.xml
odoo_addons/l10n_ch_qr_bill/i18n/de.po
odoo_addons/l10n_ch_qr_bill/i18n/fr.po
odoo_addons/l10n_ch_qr_bill/i18n/it.po
odoo_addons/l10n_ch_qr_bill/i18n/l10n_ch_qr_bill.pot
odoo_addons/l10n_ch_qr_bill/models/__init__.py
odoo_addons/l10n_ch_qr_bill/models/account_invoice.py
odoo_addons/l10n_ch_qr_bill/models/report.py
odoo_addons/l10n_ch_qr_bill/models/res_bank.py
odoo_addons/l10n_ch_qr_bill/report/swissqr_report.xml
odoo_addons/l10n_ch_qr_bill/static/description/icon.png
odoo_addons/l10n_ch_qr_bill/static/src/css/report_swissqr.css
odoo_addons/l10n_ch_qr_bill/static/src/img/CH-Cross_7mm.png
odoo_addons/l10n_ch_qr_bill/tests/__init__.py
odoo_addons/l10n_ch_qr_bill/tests/test_swissqr.py
odoo_addons/l10n_ch_qr_bill/views/account_invoice_view.xml
odoo8_addon_l10n_ch_qr_bill-8.0.1.0.0.99.dev6.dist-info/METADATA
odoo8_addon_l10n_ch_qr_bill-8.0.1.0.0.99.dev6.dist-info/WHEEL
odoo8_addon_l10n_ch_qr_bill-8.0.1.0.0.99.dev6.dist-info/namespace_packages.txt
odoo8_addon_l10n_ch_qr_bill-8.0.1.0.0.99.dev6.dist-info/top_level.txt
odoo8_addon_l10n_ch_qr_bill-8.0.1.0.0.99.dev6.dist-info/RECORD
