Metadata-Version: 2.1
Name: odoo8-addon-l10n-ch-qr-bill
Version: 8.0.1.0.0.99.dev6
Summary: Print QR-bill for your invoices [Backport from Odoo 10.0]
Home-page: https://github.com/OCA/l10n-switzerland
Author: Camptocamp,Odoo Community Association (OCA)
Author-email: support@odoo-community.org
License: LGPL-3
Platform: UNKNOWN
Classifier: Programming Language :: Python
Classifier: Framework :: Odoo
Classifier: License :: OSI Approved :: GNU Lesser General Public License v3 (LGPLv3)
Requires-Python: ~=2.7
Requires-Dist: odoo (<9.0a,>=8.0a)
